deltamesh_fabric/dataprep.py
deltamesh_fabric/write.py
deltamesh_core-0.1.7.dist-info/LICENSE
deltamesh_core-0.1.7.dist-info/METADATA
deltamesh_core-0.1.7.dist-info/WHEEL
deltamesh_core-0.1.7.dist-info/top_level.txt
deltamesh_core-0.1.7.dist-info/RECORD
